[{"unMeta":{}},[{"t":"Para","c":[{"t":"Str","c":"{"}]},{"t":"Para","c":[{"t":"Str","c":"“business”:["}]},{"t":"Para","c":[{"t":"Str","c":"{"}]},{"t":"Para","c":[{"t":"Str","c":"\"nome\":"},{"t":"Space","c":[]},{"t":"Str","c":"\"Princesa"},{"t":"Space","c":[]},{"t":"Str","c":"Cosméticos\","}]},{"t":"Para","c":[{"t":"Str","c":"\"information\":"},{"t":"Space","c":[]},{"t":"Str","c":"“151"},{"t":"Space","c":[]},{"t":"Str","c":"Benedito"},{"t":"Space","c":[]},{"t":"Str","c":"Pires"},{"t":"Space","c":[]},{"t":"Str","c":"Street”,"}]},{"t":"Para","c":[{"t":"Str","c":"“icon”:"},{"t":"Space","c":[]},{"t":"Str","c":"“https://detutto.com.br/custom/domain_1/image_files/61_photo_1634.jpg”"}]},{"t":"Para","c":[{"t":"Str","c":"},"}]},{"t":"Para","c":[{"t":"Str","c":"{"}]},{"t":"Para","c":[{"t":"Str","c":"\"nome\":"},{"t":"Space","c":[]},{"t":"Str","c":"\"Marcatto"},{"t":"Space","c":[]},{"t":"Str","c":"Centro"},{"t":"Space","c":[]},{"t":"Str","c":"Técnico"},{"t":"Space","c":[]},{"t":"Str","c":"Automotivo\","}]},{"t":"Para","c":[{"t":"Str","c":"\"information\":"},{"t":"Space","c":[]},{"t":"Str","c":"“32"},{"t":"Space","c":[]},{"t":"Str","c":"Luiz"},{"t":"Space","c":[]},{"t":"Str","c":"Pereira"},{"t":"Space","c":[]},{"t":"Str","c":"Street”,"}]},{"t":"Para","c":[{"t":"Str","c":"“icon”:"},{"t":"Space","c":[]},{"t":"Str","c":"“https://yt3.ggpht.com/ytc/AAUvwniLi8JasWtL2yJenvN9sw-DQRndZth95Sv_A3Pg=s900-c-k-c0x00ffffff-no-rj”"}]},{"t":"Para","c":[{"t":"Str","c":"},"}]},{"t":"Para","c":[{"t":"Str","c":"{"}]},{"t":"Para","c":[{"t":"Str","c":"\"nome\":"},{"t":"Space","c":[]},{"t":"Str","c":"\"Daiso\","}]},{"t":"Para","c":[{"t":"Str","c":"\"information\":"},{"t":"Space","c":[]},{"t":"Str","c":"“25"},{"t":"Space","c":[]},{"t":"Str","c":"Campolim"},{"t":"Space","c":[]},{"t":"Str","c":"Street”,"}]},{"t":"Para","c":[{"t":"Str","c":"“icon”:"},{"t":"Space","c":[]},{"t":"Str","c":"“https://encrypted-tbn0.gstatic.com/images?q=tbn:ANd9GcQ17OvrgI4VsvPvRv7jN4ihaS_iFtwNJp_t4yAR_5HpjodC0tXVRpDPJZg5EzwXm9494WQ&usqp=CAU”"}]},{"t":"Para","c":[{"t":"Str","c":"},"}]},{"t":"Para","c":[{"t":"Str","c":"{"}]},{"t":"Para","c":[{"t":"Str","c":"\"nome\":"},{"t":"Space","c":[]},{"t":"Str","c":"\"Camicado\","}]},{"t":"Para","c":[{"t":"Str","c":"\"information\":"},{"t":"Space","c":[]},{"t":"Str","c":"“45"},{"t":"Space","c":[]},{"t":"Str","c":"Campolim"},{"t":"Space","c":[]},{"t":"Str","c":"Street”,"}]},{"t":"Para","c":[{"t":"Str","c":"“icon”:"},{"t":"Space","c":[]},{"t":"Str","c":"“https://lh3.googleusercontent.com/proxy/x65o6wiK0AgtWPWfrX37m_8_Px0fQXJ6Ud-lAJh3lOMBQT3rVegNy2Txp88R2uKtIS6v3tE0cL7aV-y30-_0pskuaEcaGuJ-zjldNIM”"}]},{"t":"Para","c":[{"t":"Str","c":"}"}]},{"t":"Para","c":[{"t":"Str","c":"]"}]},{"t":"Para","c":[{"t":"Str","c":"}"}]}]]